package/__init__.py
package/sinuiMSP.py
sinuiMSP-1.1.dist-info/METADATA
sinuiMSP-1.1.dist-info/WHEEL
sinuiMSP-1.1.dist-info/top_level.txt
sinuiMSP-1.1.dist-info/RECORD
